nakdimon_onnx/__init__.py
nakdimon_onnx/config.json
nakdimon_onnx/config.py
nakdimon_onnx/model.py
nakdimon_onnx-0.1.0.dist-info/METADATA
nakdimon_onnx-0.1.0.dist-info/WHEEL
nakdimon_onnx-0.1.0.dist-info/licenses/LICENSE
nakdimon_onnx-0.1.0.dist-info/RECORD
