Metadata-Version: 2.4
Name: nakdimon-onnx
Version: 0.1.0
Summary: Hebrew diacritics with onnxruntime
Project-URL: home, https://github.com/thewh1teagle/nakdimon-onnx
Author-email: thewh1teagle <61390950+thewh1teagle@users.noreply.github.com>
License-File: LICENSE
Requires-Python: <3.13,>=3.9
Requires-Dist: onnxruntime>=1.20.1
